rag_helper/__init__.py
rag_helper/data.py
rag_helper/db.py
rag_helper/embeddings.py
rag_helper/eval.py
rag_helper/gemini_helper.py
rag_helper/models.py
rag_helper/query.py
rag_helper/string_helpers.py
rag_helper/synthetic.py
rag_helper-0.0.8.dist-info/METADATA
rag_helper-0.0.8.dist-info/WHEEL
rag_helper-0.0.8.dist-info/RECORD
