Metadata-Version: 2.1
Name: rag-helper
Version: 0.0.8
Summary: 
Author: contact.nampham.work
Author-email: contact.nampham.work@gmail.com
Requires-Python: >=3.9,<4.0
Classifier: Programming Language :: Python :: 3
Classifier: Programming Language :: Python :: 3.9
Classifier: Programming Language :: Python :: 3.10
Classifier: Programming Language :: Python :: 3.11
Classifier: Programming Language :: Python :: 3.12
Requires-Dist: google-generativeai (>=0.7.0,<0.8.0)
Requires-Dist: instructor (>=1.3.3,<2.0.0)
Requires-Dist: jsonref (>=1.1.0,<2.0.0)
Requires-Dist: lancedb (>=0.8.2,<0.9.0)
Requires-Dist: numpy (==1.26.4)
Requires-Dist: optimum[onnxruntime] (>=1.20.0,<2.0.0)
Requires-Dist: sentence-transformers (>=3.0.1,<4.0.0)
Requires-Dist: tabulate (>=0.9.0,<0.10.0)
Requires-Dist: tantivy (>=0.22.0,<0.23.0)
Requires-Dist: torch (>=2.3.1+cpu,<3.0.0)
